{
  "rank": 30,
  "title": "Slackjaw Cherophobia",
  "clip_file": "30-slackjaw-cherophobia-01-36-00.000.mp4",
  "source_path": "D:\\Cackle\\Raw VODs\\Slackjaw Cherophobia 2809668067-697386570-645a56eb-f951-410d-8a27-ff2939b1d51c.mp4",
  "source_start_seconds": 5760.0,
  "source_end_seconds": 5810.0,
  "source_peak_seconds": 5775.0,
  "source_start_timestamp": "01:36:00",
  "source_end_timestamp": "01:36:50",
  "source_peak_timestamp": "01:36:15",
  "score": 74.1,
  "reason": "chat: chat spike +9 messages, 9 active chatter(s)"
}